chronobio/__init__.py
chronobio/killall.py
chronobio/game/__init__.py
chronobio/game/constants.py
chronobio/game/employee.py
chronobio/game/exceptions.py
chronobio/game/farm.py
chronobio/game/field.py
chronobio/game/game.py
chronobio/game/loan.py
chronobio/game/location.py
chronobio/game/server.py
chronobio/game/soup_factory.py
chronobio/game/tractor.py
chronobio/game/vegetable.py
chronobio/network/__init__.py
chronobio/network/client.py
chronobio/network/data_handler.py
chronobio/network/server.py
chronobio/viewer/__init__.py
chronobio/viewer/__main__.py
chronobio/viewer/constants.py
chronobio/viewer/farm.py
chronobio/viewer/farm_background.py
chronobio/viewer/score.py
chronobio/viewer/viewer.py
chronobio/viewer/window.py
chronobio/viewer/images/blocked.png
chronobio/viewer/images/closed.png
chronobio/viewer/images/drops.png
chronobio/viewer/images/drought.png
chronobio/viewer/images/factory_small.png
chronobio/viewer/images/farm.png
chronobio/viewer/images/farmer.png
chronobio/viewer/images/field.jpg
chronobio/viewer/images/fire.png
chronobio/viewer/images/frost.png
chronobio/viewer/images/grass.jpeg
chronobio/viewer/images/leek.png
chronobio/viewer/images/onion.png
chronobio/viewer/images/potato.png
chronobio/viewer/images/soup.png
chronobio/viewer/images/tomato.png
chronobio/viewer/images/tractor.png
chronobio/viewer/images/transparent.png
chronobio/viewer/images/zucchini.png
chronobio-1.3.0.dist-info/LICENSE
chronobio-1.3.0.dist-info/METADATA
chronobio-1.3.0.dist-info/WHEEL
chronobio-1.3.0.dist-info/top_level.txt
chronobio-1.3.0.dist-info/RECORD
