Metadata-Version: 2.2
Name: chronobio
Version: 1.3.0
Summary: Chronobio programming game
Author-email: Vincent Poulailleau <vpoulailleau@gmail.com>
License: BSD-3-Clause
Project-URL: Source code, https://github.com/vpoulailleau/chronobio
Project-URL: Repository, https://github.com/vpoulailleau/chronobio
Project-URL: Documentation, https://github.com/vpoulailleau/chronobio/README.md
Keywords: chronobio,game
Classifier: Development Status :: 4 - Beta
Classifier: Intended Audience :: Developers
Classifier: License :: OSI Approved :: BSD License
Classifier: Natural Language :: English
Classifier: Programming Language :: Python :: 3
Classifier: Programming Language :: Python :: 3.10
Classifier: Programming Language :: Python :: 3.11
Classifier: Programming Language :: Python :: 3.12
Classifier: Programming Language :: Python :: 3.13
Classifier: Programming Language :: Python :: 3.14
Classifier: Topic :: Utilities
Requires-Python: >=3.10
License-File: LICENSE
Requires-Dist: arcade>=3.0
Requires-Dist: psutil>=7.0
Provides-Extra: dev
Requires-Dist: pytest; extra == "dev"
Requires-Dist: pytest-cov; extra == "dev"
Requires-Dist: python-dev-tools>=2023; extra == "dev"
Requires-Dist: pre-commit<4,>=3; extra == "dev"
Requires-Dist: pyinstrument; extra == "dev"
